{"name":"emptyFieldsLogin","id":"TestLoginLogout:emptyFieldsLogin","testCaseName":"TestLoginLogout","testSteps":[{"number":1,"description":"Empty fields login ","duration":6681,"startTime":1541870086155,"result":"SUCCESS","precondition":false,"children":[{"number":2,"description":"Test 3: Empty fields login","duration":6681,"startTime":1541870078225,"screenshots":[{"screenshot":"ca1dcf8b4666daae21860129b8e2feed18bc18d4dc5af0f8a13fba61cd538aff.png"}],"result":"SUCCESS","precondition":false}]}],"userStory":{"id":"common.Application.SomeFeature","storyName":"Some feature","storyClassName":"common.Application$SomeFeature","path":"common.Application","type":"story"},"featureTag":{"name":"Application/Some feature","type":"story"},"title":"Empty fields login","tags":[{"name":"Application/Some feature","type":"story"}],"startTime":1541870086155,"duration":0,"dataTable":{"headers":["url","username","password","invalidUsername","invalidPassword","validEmail","validName","validMessage","invalidEmail","invalidName","invalidMessage"],"rows":[{"values":["https://www.demoblaze.com/","Marius91!","Marius91!","Marius91","Marius91","marius@yahoo.com","Marius","Salut","!$%%^*(()!","!$%%^*(()!","!$%%^*(()!"],"result":"SUCCESS"}],"predefinedRows":false,"dataSetDescriptors":[{"startRow":0,"rowCount":0}]},"manual":false,"result":"SUCCESS"}